stealth_key_tool/__init__.py
stealth_key_tool/key_tool_cli.py
stealth_key_tool/stealth_key_tool.py
stealth_key_tool/version.py
stealth_key_tool/bip32utils/BIP32Key.py
stealth_key_tool/bip32utils/Base58.py
stealth_key_tool/bip32utils/__init__.py
stealth_key_tool/bip32utils/bip32gen.py
stealth_key_tool/bip39/__init__.py
stealth_key_tool/bip39/bip39.py
stealth_key_tool/bip39/bitfield.py
stealth_key_tool/bip39/english.py
stealth_key_tool/pbkdf2/__init__.py
stealth_key_tool/pbkdf2/pbkdf2.py
stealth_key_tool-0.4.3.dist-info/LICENSE
stealth_key_tool-0.4.3.dist-info/METADATA
stealth_key_tool-0.4.3.dist-info/WHEEL
stealth_key_tool-0.4.3.dist-info/entry_points.txt
stealth_key_tool-0.4.3.dist-info/top_level.txt
stealth_key_tool-0.4.3.dist-info/RECORD
