Metadata-Version: 2.1
Name: stealth_key_tool
Version: 0.4.3
Summary: A simplified wrapper for working with HD wallets
Home-page: https://github.com/Stealth-R-D-LLC/stealth-key-tool
Author: James Stroud
Author-email: James Stroud <stealthsend@stealth-coin.com>
License: Copyright (c) 2022 2024, James Stroud
Project-URL: homepage, https://github.com/Stealth-R-D-LLC/stealth-key-tool
Keywords: bip32 bip39 bip44 cryptocurrencies
Classifier: Programming Language :: Python :: 3
Classifier: License :: OSI Approved :: MIT License
Classifier: Operating System :: OS Independent
License-File: LICENSE
Requires-Dist: ecdsa
Requires-Dist: pycryptodome
